{"categoryGroup": "F\u00e4cher", "categories": ["Handf\u00e4cher", "Wandf\u00e4cher"], "variationThemes": ["L\u00e4nge", "Material", "Farbe"], "attributes": [{"name": "Set-Typ", "attributeGroup": "Artikelbezeichnung", "type": "STRING", "multiValue": false, "featureRelevance": ["TITLE"], "relevance": "LOW", "description": "", "exampleValues": ["Set", "Spar-Set"], "reference": ""}, {"name": "Serie", "attributeGroup": "Serie", "type": "STRING", "multiValue": false, "featureRelevance": [], "relevance": "LOW", "description": "", "exampleValues": [], "reference": ""}, {"name": "Set-Info", "attributeGroup": "Artikelbezeichnung", "type": "STRING", "multiValue": true, "featureRelevance": ["TITLE"], "relevance": "LOW", "description": "", "exampleValues": [], "reference": ""}, {"name": "Materialzusammensetzung", "attributeGroup": "Material", "type": "STRING", "multiValue": false, "featureRelevance": ["PRODUCT_DETAILS"], "relevance": "LOW", "description": "", "exampleValues": [], "reference": ""}, {"name": "Besondere Merkmale", "attributeGroup": "Artikelbezeichnung", "type": "STRING", "multiValue": false, "featureRelevance": ["TITLE"], "relevance": "HIGH", "description": "", "exampleValues": ["mit Blumenprint", "mit floralem Print, Schwarz", "mit rosafarbener Quaste", "mit Schmetterlingen", "mit feiner Quaste"], "reference": ""}, {"name": "Optik", "attributeGroup": "Optik / Stil", "type": "STRING", "multiValue": true, "featureRelevance": ["PRODUCT_DETAILS"], "relevance": "HIGH", "description": "", "exampleValues": ["bedruckt", "gebl\u00fcmt", "leicht gl\u00e4nzend", "Leinenoptik", "kariert"], "reference": ""}, {"name": "L\u00e4nge", "attributeGroup": "Ma\u00dfangaben", "type": "FLOAT", "multiValue": false, "unit": "cm", "unitDisplayName": "Zentimeter", "featureRelevance": ["VARIATION_THEME", "PRODUCT_DETAILS"], "relevance": "HIGH", "description": "", "reference": ""}, {"name": "Farbe", "attributeGroup": "Farbe", "type": "STRING", "multiValue": false, "featureRelevance": ["VARIATION_THEME", "TOPINFO", "PRODUCT_DETAILS"], "relevance": "HIGH", "description": "", "exampleValues": ["schwarz", "bunt", "rosa", "blau", "naturfarben"], "reference": ""}, {"name": "Material", "attributeGroup": "Material", "type": "STRING", "multiValue": false, "featureRelevance": ["VARIATION_THEME", "FILTER", "PRODUCT_DETAILS"], "relevance": "HIGH", "description": "", "exampleValues": ["Kunststoff", "Holz", "Papier", "Seide", "Aluminium"], "reference": ""}, {"name": "Grundfarbe", "attributeGroup": "Farbe", "type": "STRING", "multiValue": false, "allowedValues": ["lila", "gelb", "natur", "schwarz", "gr\u00fcn", "silberfarben", "grau", "blau", "braun", "orange", "wei\u00df", "goldfarben", "rot", "bunt", "rosa"], "featureRelevance": ["FILTER"], "relevance": "HIGH", "description": "", "reference": ""}, {"name": "Geschlecht", "attributeGroup": "Allgemein", "type": "STRING", "multiValue": false, "allowedValues": ["neutral", "m\u00e4nnlich", "weiblich"], "featureRelevance": ["NAVIGATION"], "relevance": "HIGH", "description": "", "reference": ""}, {"name": "Zielgruppe", "attributeGroup": "Allgemein", "type": "STRING", "multiValue": false, "allowedValues": ["zielgruppenunabh\u00e4ngig", "Babys", "Jugendliche", "Kinder", "Erwachsene"], "featureRelevance": ["NAVIGATION"], "relevance": "HIGH", "description": "", "reference": ""}], "lastModified": "2020-12-03T02:28:57.032Z"}