{"categoryGroup": "Haltegriffe", "categories": ["Wandgriff", "Hoverboard-Haltestange", "Bett - Aufstehhilfe", "Haltegriff", "Badewannengriff", "Trampolin-Haltestange", "Seitenwandgriff", "Teleskopgriff", "Winkel-Haltegriff", "St\u00fctzklappgriff", "Badewannen-Einstiegshilfe", "WC-Aufstehhilfe"], "variationThemes": ["L\u00e4nge", "Breite", "Verstellbarkeit", "L\u00e4nge maximal", "Material", "Farbe", "Oberfl\u00e4chenbearbeitung", "L\u00e4nge minimal", "Tiefe", "Oberfl\u00e4chenbeschichtung", "Anzahl Teile"], "attributes": [{"name": "Verstellbarkeit", "attributeGroup": "Produktdetails", "type": "STRING", "multiValue": false, "featureRelevance": ["VARIATION_THEME", "PRODUCT_DETAILS"], "relevance": "LOW", "description": "", "exampleValues": ["4-fach verstellbar", "mehrfach verstellbar", "5-fach verstellbar", "6-fach verstellbar", "7-fach verstellbar"], "reference": ""}, {"name": "L\u00e4nge maximal", "attributeGroup": "Ma\u00dfangaben", "type": "FLOAT", "multiValue": false, "unit": "cm", "unitDisplayName": "Zentimeter", "featureRelevance": ["VARIATION_THEME", "PRODUCT_DETAILS"], "relevance": "LOW", "description": "", "reference": ""}, {"name": "L\u00e4nge minimal", "attributeGroup": "Ma\u00dfangaben", "type": "FLOAT", "multiValue": false, "unit": "cm", "unitDisplayName": "Zentimeter", "featureRelevance": ["VARIATION_THEME", "PRODUCT_DETAILS"], "relevance": "LOW", "description": "", "reference": ""}, {"name": "Set-Info", "attributeGroup": "Artikelbezeichnung", "type": "STRING", "multiValue": false, "featureRelevance": [], "relevance": "LOW", "description": "", "exampleValues": [], "reference": ""}, {"name": "Winkel", "attributeGroup": "Produktdetails", "type": "INTEGER", "multiValue": false, "unit": "\u00b0", "unitDisplayName": "Grad", "featureRelevance": ["PRODUCT_DETAILS"], "relevance": "LOW", "description": "", "reference": ""}, {"name": "Serie Technischer Name", "attributeGroup": "Serie", "type": "STRING", "multiValue": false, "featureRelevance": [], "relevance": "LOW", "description": "", "exampleValues": ["MS#009333 pedalo\u00c2\u00ae 52", "Deskfit Lauftraining"], "reference": ""}, {"name": "Set-Typ", "attributeGroup": "Artikelbezeichnung", "type": "STRING", "multiValue": false, "featureRelevance": [], "relevance": "LOW", "description": "", "exampleValues": ["Set", "Spar-Set"], "reference": ""}, {"name": "Herstellergarantie", "attributeGroup": "Hinweise", "type": "STRING", "multiValue": false, "featureRelevance": ["PRODUCT_DETAILS"], "relevance": "LOW", "description": "", "exampleValues": ["10 Jahre gem\u00e4\u00df den Garantie-Bedingungen", "7 Jahre gem\u00e4\u00df den Garantie-Bedingungen", "5 Jahre gem\u00e4\u00df den Garantie-Bedingungen", "6 Jahre gem\u00e4\u00df den Garantie-Bedingungen", "8 Jahre gem\u00e4\u00df den Garantie-Bedingungen"], "reference": ""}, {"name": "Serie", "attributeGroup": "Serie", "type": "STRING", "multiValue": false, "featureRelevance": [], "relevance": "MEDIUM", "description": "", "exampleValues": ["Secura", "Serie 250", "Boston", "Serie 400 Steel", "Comfort"], "reference": ""}, {"name": "Griffl\u00e4nge", "attributeGroup": "Ma\u00dfangaben", "type": "FLOAT", "multiValue": false, "unit": "cm", "unitDisplayName": "Zentimeter", "featureRelevance": ["PRODUCT_DETAILS"], "relevance": "LOW", "description": "", "reference": ""}, {"name": "L\u00e4nge", "attributeGroup": "Ma\u00dfangaben", "type": "FLOAT", "multiValue": false, "unit": "cm", "unitDisplayName": "Zentimeter", "featureRelevance": ["VARIATION_THEME", "PRODUCT_DETAILS"], "relevance": "MEDIUM", "description": "", "reference": ""}, {"name": "Breite", "attributeGroup": "Ma\u00dfangaben", "type": "FLOAT", "multiValue": false, "unit": "cm", "unitDisplayName": "Zentimeter", "featureRelevance": ["VARIATION_THEME", "PRODUCT_DETAILS"], "relevance": "HIGH", "description": "", "reference": ""}, {"name": "Besondere Merkmale", "attributeGroup": "Artikelbezeichnung", "type": "STRING", "multiValue": false, "featureRelevance": ["TITLE"], "relevance": "HIGH", "description": "", "exampleValues": ["Edelstahl", "in wei\u00df", "chrom", "42.6 x 70 x 7 cm", "58.7 x 23.6 x 7 cm"], "reference": ""}, {"name": "Tiefe", "attributeGroup": "Ma\u00dfangaben", "type": "FLOAT", "multiValue": false, "unit": "cm", "unitDisplayName": "Zentimeter", "featureRelevance": ["VARIATION_THEME", "PRODUCT_DETAILS"], "relevance": "LOW", "description": "", "reference": ""}, {"name": "Anzahl Teile", "attributeGroup": "Produktdetails", "type": "INTEGER", "multiValue": false, "featureRelevance": ["VARIATION_THEME"], "relevance": "LOW", "description": "", "reference": ""}, {"name": "Oberfl\u00e4chenbeschichtung", "attributeGroup": "Farbe & Material", "type": "STRING", "multiValue": false, "featureRelevance": ["VARIATION_THEME", "PRODUCT_DETAILS"], "relevance": "LOW", "description": "", "exampleValues": ["verchromt", "pulverbeschichtet", "verzinkt"], "reference": ""}, {"name": "Sprachen Bedienungs-/Aufbauanleitung", "attributeGroup": "Hinweise", "type": "STRING", "multiValue": true, "featureRelevance": ["PRODUCT_DETAILS"], "relevance": "LOW", "description": "", "exampleValues": ["Deutsch (DE)", "Franz\u00f6sisch (FR)", "Italienisch (IT)", "Norwegisch (NO)", "Litauisch (LT)"], "reference": ""}, {"name": "Eigenschaften", "attributeGroup": "Produktdetails", "type": "STRING", "multiValue": true, "featureRelevance": ["PRODUCT_DETAILS"], "relevance": "LOW", "description": "", "exampleValues": ["l\u00e4ngenverstellbar", "biegsam"], "reference": ""}, {"name": "Oberfl\u00e4chenbearbeitung", "attributeGroup": "Farbe & Material", "type": "STRING", "multiValue": false, "featureRelevance": ["VARIATION_THEME", "PRODUCT_DETAILS"], "relevance": "LOW", "description": "", "exampleValues": ["hochglanzpoliert", "poliert", "angeraut", "geb\u00fcrstet", "ummantelt"], "reference": ""}, {"name": "Materialeigenschaften", "attributeGroup": "Farbe & Material", "type": "STRING", "multiValue": true, "featureRelevance": ["PRODUCT_DETAILS"], "relevance": "LOW", "description": "", "exampleValues": ["antibakteriell", "rutschfest"], "reference": ""}, {"name": "Gewicht", "attributeGroup": "Ma\u00dfangaben", "type": "FLOAT", "multiValue": false, "unit": "g", "unitDisplayName": "Gramm", "featureRelevance": ["PRODUCT_DETAILS"], "relevance": "MEDIUM", "description": "", "reference": ""}, {"name": "Einsatzbereich", "attributeGroup": "Produktdetails", "type": "STRING", "multiValue": true, "featureRelevance": ["PRODUCT_DETAILS"], "relevance": "MEDIUM", "description": "", "exampleValues": ["Badezimmer", "Indoor", "Outdoor"], "reference": ""}, {"name": "Art Montage", "attributeGroup": "Hinweise", "type": "STRING", "multiValue": true, "featureRelevance": ["PRODUCT_DETAILS"], "relevance": "HIGH", "description": "", "exampleValues": ["Wandmontage", "bohren", "kleben", "Saugn\u00e4pfe", "klemmen"], "reference": ""}, {"name": "Geschlecht", "attributeGroup": "Allgemein", "type": "STRING", "multiValue": false, "allowedValues": ["neutral", "m\u00e4nnlich", "weiblich"], "featureRelevance": ["NAVIGATION"], "relevance": "HIGH", "description": "", "reference": ""}, {"name": "Durchmesser Griff", "attributeGroup": "Ma\u00dfangaben", "type": "FLOAT", "multiValue": false, "unit": "mm", "unitDisplayName": "Millimeter", "featureRelevance": ["PRODUCT_DETAILS"], "relevance": "LOW", "description": "", "reference": ""}, {"name": "Belastbarkeit maximal", "attributeGroup": "Produktdetails", "type": "FLOAT", "multiValue": false, "unit": "kg", "unitDisplayName": "Kilogramm", "featureRelevance": ["TITLE", "PRODUCT_DETAILS"], "relevance": "HIGH", "description": "", "reference": ""}, {"name": "Ausstattung", "attributeGroup": "Produktdetails", "type": "STRING", "multiValue": true, "featureRelevance": ["PRODUCT_DETAILS"], "relevance": "LOW", "description": "", "exampleValues": ["ergonomisch geformte Grifffl\u00e4che", "Antirutschbeschichtung", "Ampel-System", "Seifenablage", "Vakuum-Kipphebel"], "reference": ""}, {"name": "Lieferumfang", "attributeGroup": "Hinweise", "type": "STRING", "multiValue": true, "featureRelevance": ["PRODUCT_DETAILS"], "relevance": "LOW", "description": "", "exampleValues": ["Befestigungsmaterial", "Montageanleitung", "Bedienungsanleitung", "Gelenkadapter"], "reference": ""}, {"name": "Material", "attributeGroup": "Farbe & Material", "type": "STRING", "multiValue": false, "featureRelevance": ["VARIATION_THEME", "FILTER", "PRODUCT_DETAILS"], "relevance": "HIGH", "description": "", "exampleValues": ["Edelstahl", "Aluminium", "Kunststoff", "Metall", "Zinkdruckguss"], "reference": ""}, {"name": "Grundfarbe", "attributeGroup": "Farbe & Material", "type": "STRING", "multiValue": true, "allowedValues": ["lila", "gelb", "natur", "schwarz", "gr\u00fcn", "silberfarben", "grau", "blau", "braun", "orange", "wei\u00df", "goldfarben", "rot", "bunt", "rosa"], "featureRelevance": ["FILTER"], "relevance": "HIGH", "description": "", "reference": ""}, {"name": "Farbe", "attributeGroup": "Farbe & Material", "type": "STRING", "multiValue": false, "featureRelevance": ["VARIATION_THEME", "PRODUCT_DETAILS"], "relevance": "HIGH", "description": "", "exampleValues": ["silberfarben", "wei\u00df", "chromfarben", "schwarz", "edelstahlfarben"], "reference": ""}, {"name": "Zielgruppe", "attributeGroup": "Allgemein", "type": "STRING", "multiValue": false, "allowedValues": ["zielgruppenunabh\u00e4ngig", "Babys", "Jugendliche", "Kinder", "Erwachsene"], "featureRelevance": ["NAVIGATION"], "relevance": "HIGH", "description": "", "reference": ""}], "lastModified": "2020-12-04T03:49:30.974Z"}