{"categoryGroup": "Overalls", "categories": ["Overall", "Playsuit", "Strandoverall", "Fleeceoverall", "Jumpsuit", "Pl\u00fcschoverall", "Schneeoverall", "Kurzoverall", "Schlafanzug (Overalls)", "Strampler", "Culotte-Overall", "Neckholder-Overall", "Bandeauoverall", "Nickioverall", "Softshelloverall", "Schlafoverall", "Umstandsoverall", "Regenoverall", "Spieler", "Motorradkombi", "Maleranzug", "7/8-Overall", "Catsuit (Overalls)", "Relaxanzug (Overalls)", "Hausanzug (Overalls)", "Loungeanzug (Overalls)", "Freizeitanzug (Overalls)", "Homesuit (Overalls)"], "variationThemes": ["Ausgabegr\u00f6\u00dfe", "Farbe Packst\u00fcck 2", "Material", "K\u00f6rbchengr\u00f6\u00dfe", "Farbe Packst\u00fcck 3", "Materialart", "Unterbrustumfang", "Schnittform L\u00e4nge", "Farbe", "Anzahl Teile"], "attributes": [{"name": "Anzahl Taschen", "attributeGroup": "Details", "type": "INTEGER", "multiValue": false, "unit": "St.", "unitDisplayName": "St\u00fcck", "featureRelevance": ["PRODUCT_DETAILS"], "relevance": "LOW", "description": "", "reference": ""}, {"name": "Art Protektoren", "attributeGroup": "Details", "type": "STRING", "multiValue": true, "featureRelevance": ["PRODUCT_DETAILS"], "relevance": "LOW", "description": "", "exampleValues": ["Schulterprotektoren", "Ellenbogenprotektoren", "Knieprotektoren", "R\u00fcckenprotektoren"], "reference": ""}, {"name": "Eigenschaften", "attributeGroup": "Details", "type": "STRING", "multiValue": true, "featureRelevance": ["PRODUCT_DETAILS"], "relevance": "LOW", "description": "", "exampleValues": ["herausnehmbares Innenfutter", "Weitenverstellung", "herausnehmbares Thermofutter", "Bel\u00fcftungssystem", "herausnehmbare Polsterung"], "reference": ""}, {"name": "Fu\u00dfweite", "attributeGroup": "Ma\u00dfangaben", "type": "FLOAT", "multiValue": true, "unit": "cm", "unitDisplayName": "Zentimeter", "featureRelevance": ["PRODUCT_DETAILS"], "relevance": "LOW", "description": "", "reference": ""}, {"name": "Gr\u00f6\u00dfenhinweis", "attributeGroup": "Ma\u00dfangaben", "type": "STRING", "multiValue": false, "featureRelevance": ["PRODUCT_DETAILS"], "relevance": "LOW", "description": "", "exampleValues": ["F\u00e4llt klein aus, bitte eine Gr\u00f6\u00dfe gr\u00f6\u00dfer bestellen.", "F\u00e4llt eng aus, bitte eine Gr\u00f6\u00dfe gr\u00f6\u00dfer bestellen.", "F\u00e4llt gro\u00df aus, bitte eine Gr\u00f6\u00dfe kleiner bestellen.", "F\u00e4llt sehr weit aus, bitte zwei Gr\u00f6\u00dfen kleiner bestellen.", "F\u00e4llt sehr klein aus, bitte zwei Gr\u00f6\u00dfen gr\u00f6\u00dfer bestellen."], "reference": ""}, {"name": "Herstellertechnologien", "attributeGroup": "Material", "type": "STRING", "multiValue": true, "featureRelevance": ["FILTER", "NAVIGATION", "SEARCH", "PRODUCT_DETAILS"], "relevance": "LOW", "description": "", "exampleValues": ["PFC FREE", "TEXAPORE ECOSPHERE", "bluesign\u00ae", "MICROGUARD ECOSPHERE", "AirVentSystem\u2122"], "recommendedValues": ["AEROREADY", "DOWN", "SNAP-IN-SYSTEM", "climacool\u00ae", "EXTRA-LONG SYSTEM ZIP", "windCELL", "RAIN.RDY", "ALTAI FLEECE MEDIUM", "NANUK 200", "MICROGUARD MAXLOFT", "Fubu tex", "TECNOPILE\u00ae", "Dri-FIT", "MICROGUARD SILVER", "SOFT SHELL STRETCH", "PFC FREE", "DOWNFIBER", "TEXAPORE Stretch", "SNUGGLE UP", "HIGH QUALITY DOWN", "STORMLOCK", "UPF Protection 30", "WIND.RDY", "TEXAPORE 4x4", "Vent Pro System", "COLD.RDY", "MICROGUARD MAXLOFT Q.M.C.", "Kids/Youth System Zip", "UV SHIELD", "climaproof\u00ae", "PlayWarm", "powerCELL", "climalite\u00ae Cotton", "ALTAI FLEECE SUPER WARM", "ColdGear\u00ae", "3-in-1 SYSTEM REGULAR", "ARMATECH PLUS", "VENTBREAK", "TEXAPORE O2", "3-in-1 SYSTEM SHORT", "FIBERCLOUD", "Stormlock Hyproof", "bluesign\u00ae", "S. CAF\u00c9\u00ae", "UPF Protection 15", "FAIR WEAR FOUNDATION", "THINSULATE", "climachill\u2122", "coolCELL", "FUNCTION 65", "NANUK 100", "ALTAI FLEECE MICRO", "NANUK 300", "dryCELL", "HyVent\u00ae", "Regular Zip for System Jackets", "Polartec\u00ae", "ZipIn!", "NANUK 150", "VENTLOFT", "WINDSTOPPER\u00ae", "QuickDry", "TEXAPORE", "UPF Protection 50", "UV-PROTECTION", "PlayIce", "climalite\u00ae", "PlayShield", "ACS TIGHT", "S-FRESH", "climaheat\u2122", "HEAT.RDY", "NANUK DYNAMIC", "TECNOWOOL", "Allseasongear\u00ae", "Q.M.C.", "GORE-TEX\u00ae", "SUPPLEX\u00ae", "techfit\u2122", "ACS", "Short Zip for System Jackets", "Stormlock Active", "DRYNETIC", "warmCELL", "PRIMALOFT\u00ae BLACK ECO", "climalite\u00ae+", "climawarm\u00ae", "VENTURI"], "reference": ""}, {"name": "Hinweis Ma\u00dfangaben", "attributeGroup": "Ma\u00dfangaben", "type": "STRING", "multiValue": false, "featureRelevance": ["PRODUCT_DETAILS"], "relevance": "LOW", "description": "", "exampleValues": ["Alle Angaben sind ca.-Ma\u00dfe."], "reference": ""}, {"name": "Kapuze", "attributeGroup": "Details", "type": "STRING", "multiValue": false, "featureRelevance": ["PRODUCT_DETAILS"], "relevance": "LOW", "description": "", "exampleValues": ["mit Kapuze", "ohne Kapuze"], "reference": ""}, {"name": "Kapuzendetails", "attributeGroup": "Details", "type": "STRING", "multiValue": true, "featureRelevance": ["PRODUCT_DETAILS"], "relevance": "LOW", "description": "", "exampleValues": ["abnehmbar", "abnehmbares Fellimitat", "mit Kordelzug", "im Kragen verstaubar", "mit \u00d6hrchen"], "reference": ""}, {"name": "Materialhinweis", "attributeGroup": "Material", "type": "STRING", "multiValue": false, "featureRelevance": ["PRODUCT_DETAILS"], "relevance": "LOW", "description": "", "exampleValues": ["enth\u00e4lt nichttextile Teile tierischen Ursprungs"], "reference": ""}, {"name": "Oberschenkelweite", "attributeGroup": "Ma\u00dfangaben", "type": "FLOAT", "multiValue": true, "unit": "cm", "unitDisplayName": "Zentimeter", "featureRelevance": ["PRODUCT_DETAILS"], "relevance": "LOW", "description": "", "reference": ""}, {"name": "Serie", "attributeGroup": "Serie", "type": "STRING", "multiValue": false, "featureRelevance": [], "relevance": "LOW", "description": "", "exampleValues": ["557205200, 557205349, 557205131, 557206145"], "reference": ""}, {"name": "Zus\u00e4tzlicher Ausschnitt", "attributeGroup": "Passform/Schnitt", "type": "STRING", "multiValue": false, "featureRelevance": ["PRODUCT_DETAILS"], "relevance": "LOW", "description": "", "exampleValues": ["mit Bindeband", "V-Ausschnitt hinten, vorn und hinten mit Spitzenbesatz", "hinten mit Rei\u00dfverschluss"], "reference": ""}, {"name": "Zus\u00e4tzlicher Verschluss", "attributeGroup": "Details", "type": "STRING", "multiValue": false, "featureRelevance": ["PRODUCT_DETAILS"], "relevance": "LOW", "description": "", "exampleValues": ["Druckknopf"], "reference": ""}, {"name": "\u00c4rmelabschlussdetails", "attributeGroup": "Passform/Schnitt", "type": "STRING", "multiValue": true, "featureRelevance": ["PRODUCT_DETAILS"], "relevance": "LOW", "description": "", "exampleValues": ["mit Gummizug", "mit Schlitz", "verstellbar", "mit Druckkn\u00f6pfen", "kontrastfarben"], "reference": ""}, {"name": "Tr\u00e4gerdetails", "attributeGroup": "Passform/Schnitt", "type": "STRING", "multiValue": true, "featureRelevance": ["PRODUCT_DETAILS"], "relevance": "LOW", "description": "", "exampleValues": ["verstellbar", "breit", "schmal", "abnehmbar", "im R\u00fccken gekreuzt"], "reference": ""}, {"name": "R\u00fcckenl\u00e4nge", "attributeGroup": "Ma\u00dfangaben", "type": "FLOAT", "multiValue": true, "unit": "cm", "unitDisplayName": "Zentimeter", "featureRelevance": ["PRODUCT_DETAILS"], "relevance": "LOW", "description": "", "reference": ""}, {"name": "\u00c4rmelabschluss", "attributeGroup": "Passform/Schnitt", "type": "STRING", "multiValue": false, "featureRelevance": ["PRODUCT_DETAILS"], "relevance": "LOW", "description": "", "exampleValues": ["1-Knopf-Manschette", "B\u00fcndchen", "abgesteppte Kante", "normaler Saum", "angesetztes B\u00fcndchen"], "reference": ""}, {"name": "\u00c4rmell\u00e4nge", "attributeGroup": "Ma\u00dfangaben", "type": "FLOAT", "multiValue": true, "unit": "cm", "unitDisplayName": "Zentimeter", "featureRelevance": ["PRODUCT_DETAILS"], "relevance": "LOW", "description": "", "reference": ""}, {"name": "Sprachen Materialzusammensetzung textiler Bestandteile", "attributeGroup": "Product Compliance", "type": "STRING", "multiValue": true, "featureRelevance": [], "relevance": "LOW", "description": "", "exampleValues": ["Franz\u00f6sisch (FR)", "Italienisch (IT)", "Norwegisch (NO)", "T\u00fcrkisch (TR)", "Englisch (EN)"], "reference": ""}, {"name": "Erf\u00fcllung Brennverhalten nach L\u00e4ndern", "attributeGroup": "Product Compliance", "type": "STRING", "multiValue": true, "featureRelevance": [], "relevance": "LOW", "description": "", "exampleValues": ["Produkt erf\u00fcllt die Vorgaben zum Brennverhalten f\u00fcr Gro\u00dfbritannien", "Produkt erf\u00fcllt die Vorgaben zum Brennverhalten f\u00fcr die Niederlande"], "reference": ""}, {"name": "Herstelleradresse (EWR) am Produkt", "attributeGroup": "Product Compliance", "type": "STRING", "multiValue": false, "featureRelevance": [], "relevance": "LOW", "description": "", "exampleValues": ["Produkt verf\u00fcgt \u00fcber eine Kennzeichnung mit der Herstelleradresse (EWR)", "Produkt verf\u00fcgt nicht \u00fcber eine Kennzeichnung mit der Herstelleradresse (EWR)"], "reference": ""}, {"name": "Sprachen Pflegezusatzinformation Produkt", "attributeGroup": "Product Compliance", "type": "STRING", "multiValue": true, "featureRelevance": [], "relevance": "LOW", "description": "", "exampleValues": ["Franz\u00f6sisch (FR)", "Italienisch (IT)", "Norwegisch (NO)", "T\u00fcrkisch (TR)", "Englisch (EN)"], "reference": ""}, {"name": "G\u00fcrtelschlaufen", "attributeGroup": "Details", "type": "BOOLEAN", "multiValue": false, "featureRelevance": ["PRODUCT_DETAILS"], "relevance": "LOW", "description": "", "reference": ""}, {"name": "Rumpfabschlussdetails", "attributeGroup": "Passform/Schnitt", "type": "STRING", "multiValue": true, "featureRelevance": ["PRODUCT_DETAILS"], "relevance": "LOW", "description": "", "exampleValues": ["mit Gummizug", "mit innenliegendem Gummizug", "mit Bindeband", "hinten", "krempelbar"], "reference": ""}, {"name": "Bundabschluss", "attributeGroup": "Passform/Schnitt", "type": "STRING", "multiValue": false, "featureRelevance": ["PRODUCT_DETAILS"], "relevance": "LOW", "description": "", "exampleValues": ["elastischer Bund", "normaler Saum", "abgesteppte Kante", "B\u00fcndchen", "Rippb\u00fcndchen"], "reference": ""}, {"name": "Rumpfabschluss", "attributeGroup": "Passform/Schnitt", "type": "STRING", "multiValue": false, "featureRelevance": ["PRODUCT_DETAILS"], "relevance": "LOW", "description": "", "exampleValues": ["normaler Saum", "elastischer Bund", "abgesteppt", "abgesteppte Kante", "gesmokt"], "reference": ""}, {"name": "Kragen", "attributeGroup": "Passform/Schnitt", "type": "STRING", "multiValue": false, "featureRelevance": ["PRODUCT_DETAILS"], "relevance": "LOW", "description": "", "exampleValues": ["Stehkragen", "ohne Kragen", "Reverskragen", "Kentkragen", "Hemdblusenkragen"], "reference": ""}, {"name": "Verschlussdetails", "attributeGroup": "Details", "type": "STRING", "multiValue": true, "featureRelevance": ["PRODUCT_DETAILS"], "relevance": "LOW", "description": "", "exampleValues": ["hinten", "vorn", "zum Binden", "verdeckt", "mit Windschutzblende"], "reference": ""}, {"name": "Taschen", "attributeGroup": "Details", "type": "STRING", "multiValue": true, "featureRelevance": ["PRODUCT_DETAILS"], "relevance": "LOW", "description": "", "exampleValues": ["Eingrifftaschen", "Rei\u00dfverschlusstaschen", "Brusttaschen", "Seitennahttaschen", "Ohne Taschen"], "reference": ""}, {"name": "Beinabschluss", "attributeGroup": "Passform/Schnitt", "type": "STRING", "multiValue": false, "featureRelevance": ["PRODUCT_DETAILS"], "relevance": "LOW", "description": "", "exampleValues": ["abgesteppte Kante", "gerader Abschluss", "normaler Saum", "abgesteppt", "B\u00fcndchen"], "reference": ""}, {"name": "Herstellerpassform", "attributeGroup": "Passform/Schnitt", "type": "STRING", "multiValue": false, "featureRelevance": ["PRODUCT_DETAILS"], "relevance": "LOW", "description": "", "exampleValues": ["normal", "Passform, Schnitt: Regular Fit", "Jumpsuit", "Overall", "Alle Angaben sind ca.- Angaben"], "reference": ""}, {"name": "Applikationen", "attributeGroup": "Details", "type": "STRING", "multiValue": true, "featureRelevance": ["PRODUCT_DETAILS"], "relevance": "LOW", "description": "", "exampleValues": ["Kn\u00f6pfe", "Druck", "Druckkn\u00f6pfe", "Logodruck", "Print"], "reference": ""}, {"name": "Leibh\u00f6he", "attributeGroup": "Passform/Schnitt", "type": "STRING", "multiValue": false, "featureRelevance": ["FILTER", "NAVIGATION", "SEARCH", "PRODUCT_DETAILS"], "relevance": "LOW", "description": "", "exampleValues": ["normal", "hoch", "komfortabel", "niedrig", "klassisch"], "recommendedValues": ["normal", "sitzt unterhalb der H\u00fcfte", "sehr niedrig", "komfortabel", "sitzt in der Taille", "niedrig", "sitzt unterhalb der Taille", "sitzt oberhalb der Taille", "klassisch", "niedriger", "sitzt leicht unterhalb der Taille", "etwas niedriger", "hoch", "sitzt auf der H\u00fcfte"], "reference": ""}, {"name": "Ausschnittdetails", "attributeGroup": "Passform/Schnitt", "type": "STRING", "multiValue": true, "featureRelevance": ["PRODUCT_DETAILS"], "relevance": "LOW", "description": "", "exampleValues": ["mit Gummizug", "Wickeloptik", "abgesteppte Kante", "mit Rei\u00dfverschluss", "Rippb\u00fcndchen"], "reference": ""}, {"name": "Schnittdetails", "attributeGroup": "Passform/Schnitt", "type": "STRING", "multiValue": true, "featureRelevance": ["PRODUCT_DETAILS"], "relevance": "LOW", "description": "", "exampleValues": ["Raffung in der Taille", "Taillennaht", "Abn\u00e4her", "Einsatz", "Passe hinten"], "reference": ""}, {"name": "Serie Technischer Name", "attributeGroup": "Serie", "type": "STRING", "multiValue": false, "featureRelevance": [], "relevance": "LOW", "description": "", "exampleValues": ["WB#OT1-8KM11122019-SO Japan", "MS#005206 LASCANA", "WB#OT1-8KM27052020-BF Cottage", "MS#014290 LASCANA", "WB#OT1-8KM26062020-SO Rose"], "reference": ""}, {"name": "Innenbeinl\u00e4nge", "attributeGroup": "Ma\u00dfangaben", "type": "FLOAT", "multiValue": true, "unit": "cm", "unitDisplayName": "Zentimeter", "featureRelevance": ["PRODUCT_DETAILS"], "relevance": "LOW", "description": "", "reference": ""}, {"name": "Bundabschlussdetails", "attributeGroup": "Passform/Schnitt", "type": "STRING", "multiValue": true, "featureRelevance": ["PRODUCT_DETAILS"], "relevance": "LOW", "description": "", "exampleValues": ["verstellbar", "mit Gummizug", "mit Bindeband", "hinten", "mit Tunnelzug"], "reference": ""}, {"name": "Farbe Packst\u00fcck 2", "attributeGroup": "Farbe", "type": "STRING", "multiValue": false, "featureRelevance": ["VARIATION_THEME", "PRODUCT_DETAILS"], "relevance": "LOW", "description": "", "exampleValues": ["wei\u00df", "gr\u00fcn", "rosa", "gepunktet", "bedruckt"], "reference": ""}, {"name": "Waschung", "attributeGroup": "Optik/Stil", "type": "STRING", "multiValue": true, "featureRelevance": ["PRODUCT_DETAILS"], "relevance": "LOW", "description": "", "exampleValues": ["Denim", "washed", "moonwashed", "enzym", "old"], "reference": ""}, {"name": "Kapuzenf\u00fctterung", "attributeGroup": "Details", "type": "STRING", "multiValue": true, "featureRelevance": ["PRODUCT_DETAILS"], "relevance": "LOW", "description": "", "exampleValues": ["gef\u00fcttert", "kontrastfarben", "Jersey", "Fleece", "Sweatware"], "reference": ""}, {"name": "\u00c4rmeldetails", "attributeGroup": "Passform/Schnitt", "type": "STRING", "multiValue": true, "featureRelevance": ["PRODUCT_DETAILS"], "relevance": "LOW", "description": "", "exampleValues": ["angeschnitten", "weit", "eingesetzt", "mit Knopf", "Fl\u00fcgel\u00e4rmel"], "reference": ""}, {"name": "Auslieferung", "attributeGroup": "Auslieferung", "type": "STRING", "multiValue": false, "featureRelevance": ["PRODUCT_DETAILS"], "relevance": "LOW", "description": "", "exampleValues": ["liegend", "h\u00e4ngend"], "reference": ""}, {"name": "Kragendetails", "attributeGroup": "Passform/Schnitt", "type": "STRING", "multiValue": true, "featureRelevance": ["PRODUCT_DETAILS"], "relevance": "LOW", "description": "", "exampleValues": ["mit Klettverschluss", "mit Fleece gef\u00fcttert", "abnehmbar", "mit Kordelz\u00fcgen", "mit Kn\u00f6pfen"], "reference": ""}, {"name": "Passform", "attributeGroup": "Passform/Schnitt", "type": "STRING", "multiValue": false, "featureRelevance": ["PRODUCT_DETAILS"], "relevance": "LOW", "description": "", "exampleValues": ["figurumspielend", "bequem", "Basic", "figurbetont", "regular fit"], "reference": ""}, {"name": "Farbe Packst\u00fcck 3", "attributeGroup": "Farbe", "type": "STRING", "multiValue": false, "featureRelevance": ["VARIATION_THEME", "PRODUCT_DETAILS"], "relevance": "LOW", "description": "", "exampleValues": ["bedruckt", "petrol", "khaki", "grau", "geringelt"], "reference": ""}, {"name": "Beinabschlussdetails", "attributeGroup": "Passform/Schnitt", "type": "STRING", "multiValue": true, "featureRelevance": ["PRODUCT_DETAILS"], "relevance": "LOW", "description": "", "exampleValues": ["mit Gummizug", "verstellbar", "mit Schlitz", "mit Rei\u00dfverschluss", "mit innenliegendem Gummizug"], "reference": ""}, {"name": "Unterbrustumfang", "attributeGroup": "Gr\u00f6\u00dfensystem", "type": "INTEGER", "multiValue": false, "allowedValues": ["130", "120", "110", "100", "135", "125", "115", "105", "90", "80", "70", "95", "85", "75", "65"], "featureRelevance": ["VARIATION_THEME", "FILTER"], "relevance": "LOW", "description": "", "reference": ""}, {"name": "Ausstattung", "attributeGroup": "Produktdetails", "type": "STRING", "multiValue": true, "featureRelevance": ["PRODUCT_DETAILS"], "relevance": "LOW", "description": "", "exampleValues": ["R\u00fcckenpolster", "Ellbogenpolster", "Kniepolster"], "reference": ""}, {"name": "Set-Typ", "attributeGroup": "Artikelbezeichnung", "type": "STRING", "multiValue": false, "featureRelevance": ["TITLE"], "relevance": "LOW", "description": "", "exampleValues": ["Packung", "Set", "Spar-Set"], "reference": ""}, {"name": "Produktkennzeichnungen", "attributeGroup": "Product Compliance", "type": "STRING", "multiValue": true, "featureRelevance": [], "relevance": "LOW", "description": "", "exampleValues": ["Artikelnummer", "Seriennummer", "Kennnummer der Partie", "Rahmennummer", "Typennummer"], "reference": ""}, {"name": "Anzahl Teile", "attributeGroup": "Artikelbezeichnung", "type": "INTEGER", "multiValue": false, "unit": "tlg.", "unitDisplayName": "Teilig", "featureRelevance": ["TITLE", "VARIATION_THEME", "FILTER", "NAVIGATION", "SEARCH"], "relevance": "LOW", "description": "", "recommendedValues": ["12", "1", "2", "3", "4", "5", "6", "7", "8", "9", "20", "10"], "reference": ""}, {"name": "Ausgabegr\u00f6\u00dfe", "attributeGroup": "Gr\u00f6\u00dfentext", "type": "STRING", "multiValue": false, "featureRelevance": ["VARIATION_THEME", "TOPINFO"], "relevance": "HIGH", "description": "", "exampleValues": ["M", "L", "S", "XL", "XS"], "reference": ""}, {"name": "Materialzusammensetzung", "attributeGroup": "Material", "type": "STRING", "multiValue": true, "featureRelevance": ["LEGAL", "PRODUCT_DETAILS"], "relevance": "HIGH", "description": "", "exampleValues": ["Obermaterial: 100% Viskose", "Obermaterial: 100% Polyester", "100\u00a0% Baumwolle", "Obermaterial: 95% Viskose, 5% Elasthan", "100% Baumwolle"], "reference": ""}, {"name": "US-Gr\u00f6\u00dfen (Nummerisch)", "attributeGroup": "Gr\u00f6\u00dfensystem", "type": "INTEGER", "multiValue": true, "allowedValues": ["00", "22", "12", "24", "14", "16", "18", "0", "1", "2", "3", "4", "5", "6", "7", "8", "9", "20", "10"], "featureRelevance": ["FILTER"], "relevance": "LOW", "description": "", "reference": ""}, {"name": "Normalgr\u00f6\u00dfen", "attributeGroup": "Gr\u00f6\u00dfensystem", "type": "INTEGER", "multiValue": true, "allowedValues": ["44", "66", "34", "56", "78", "46", "68", "36", "58", "48", "38", "70", "60", "50", "72", "40", "62", "30", "52", "74", "42", "64", "32", "54"], "featureRelevance": ["FILTER"], "relevance": "MEDIUM", "description": "", "reference": ""}, {"name": "Besondere Merkmale", "attributeGroup": "Details", "type": "STRING", "multiValue": false, "featureRelevance": ["TITLE", "PRODUCT_DETAILS"], "relevance": "MEDIUM", "description": "", "exampleValues": ["aus Bio-Baumwolle", "Overall", "in tollem Design", "empty", "mit Blumenmuster"], "reference": ""}, {"name": "Material", "attributeGroup": "Material", "type": "STRING", "multiValue": false, "featureRelevance": ["VARIATION_THEME", "FILTER", "NAVIGATION", "SEARCH"], "relevance": "HIGH", "description": "", "exampleValues": ["Baumwolle", "Polyester", "Viskose", "Materialmix", "Kunstfaser"], "recommendedValues": ["Daune", "Baumwolle", "Elasthan", "Baumwollmischung"], "reference": ""}, {"name": "Grundfarbe", "attributeGroup": "Farbe", "type": "STRING", "multiValue": true, "allowedValues": ["lila", "gelb", "natur", "schwarz", "gr\u00fcn", "silberfarben", "grau", "blau", "braun", "orange", "wei\u00df", "goldfarben", "rot", "bunt", "rosa"], "featureRelevance": ["FILTER"], "relevance": "HIGH", "description": "", "reference": ""}, {"name": "Stil", "attributeGroup": "Optik/Stil", "type": "STRING", "multiValue": false, "featureRelevance": ["FILTER", "NAVIGATION", "SEARCH", "PRODUCT_DETAILS"], "relevance": "LOW", "description": "", "exampleValues": ["casual", "modisch", "Basic", "feminin", "elegant"], "recommendedValues": ["modisch", "sportlich", "klassisch", "sexy", "casual", "elegant", "feminin"], "reference": ""}, {"name": "Ausschnitt", "attributeGroup": "Passform/Schnitt", "type": "STRING", "multiValue": false, "featureRelevance": ["PRODUCT_DETAILS"], "relevance": "LOW", "description": "", "exampleValues": ["V-Ausschnitt", "Rundhals", "Carmenausschnitt", "ohne Ausschnitt", "tiefer V-Ausschnitt"], "reference": ""}, {"name": "Anl\u00e4sse", "attributeGroup": "Allgemein", "type": "STRING", "multiValue": true, "featureRelevance": ["FILTER", "NAVIGATION", "SEARCH"], "relevance": "LOW", "description": "", "exampleValues": ["Sommermode", "Strandmode", "Casualmode", "Basic", "Wintermode"], "recommendedValues": ["Arbeitsmode", "Basic", "Festival", "Festtagsmode", "Streetwear", "Wintermode", "Dessous", "Sleepwear", "Trachtenmode", "Erotik", "Fanmode", "Outdoormode", "Abendmode", "Homewear", "Sportmode", "Herbstmode", "Strandmode", "Hochzeitsmode", "Sommermode", "Casualmode", "Businessmode", "Fr\u00fchlingsmode"], "reference": ""}, {"name": "Zielgruppe", "attributeGroup": "Allgemein", "type": "STRING", "multiValue": false, "allowedValues": ["zielgruppenunabh\u00e4ngig", "Babys", "Jugendliche", "Kinder", "Erwachsene"], "featureRelevance": ["NAVIGATION", "FILTER", "SEARCH"], "relevance": "HIGH", "description": "", "reference": ""}, {"name": "Gr\u00f6\u00dfentext", "attributeGroup": "Gr\u00f6\u00dfensystem", "type": "STRING", "multiValue": true, "featureRelevance": [], "relevance": "HIGH", "description": "", "exampleValues": [" M (US)", " S (US)", " L (US)", "38 (EU) ", "42 (EU) "], "reference": ""}, {"name": "K\u00f6rbchengr\u00f6\u00dfe", "attributeGroup": "Gr\u00f6\u00dfentext", "type": "STRING", "multiValue": false, "allowedValues": ["Cup D/DD", "Cup A/B", "Cup DD/E", "Cup A/A", "Cup D/E/F", "Cup C/D", "Cup B/C", "Cup E/F", "Cup A", "Cup AA", "Cup D/E", "Cup G/H", "Cup F/G", "Cup H", "Cup I", "Cup F", "Cup G", "Cup D", "Cup E", "Cup B", "Cup C", "Cup L", "Cup J", "Cup K", "Cup A/B/C", "Cup DD", "Cup AA/A"], "featureRelevance": ["VARIATION_THEME"], "relevance": "LOW", "description": "", "reference": ""}, {"name": "Materialeigenschaften", "attributeGroup": "Material", "type": "STRING", "multiValue": true, "featureRelevance": ["FILTER", "NAVIGATION", "SEARCH", "PRODUCT_DETAILS"], "relevance": "LOW", "description": "", "exampleValues": ["pflegeleicht", "elastisch", "wasserdicht", "winddicht", "Stretch"], "recommendedValues": ["schnell trocknend", "w\u00e4rmend", "elastisch", "wasserabweisend", "w\u00e4rmeisolierend", "k\u00fchlend", "wasserdicht", "antibakteriell", "windabweisend", "winddicht", "atmungsaktiv"], "reference": ""}, {"name": "Set-Info", "attributeGroup": "Artikelbezeichnung", "type": "STRING", "multiValue": true, "featureRelevance": ["TITLE"], "relevance": "LOW", "description": "", "exampleValues": ["2er-Pack", "3er-Pack", "mit T-Shirt", "mit Bindeband", "mit Bindeg\u00fcrtel"], "reference": ""}, {"name": "Schuhgr\u00f6\u00dfe UK", "attributeGroup": "Gr\u00f6\u00dfensystem", "type": "INTEGER", "multiValue": true, "allowedValues": ["7,5", "8,5", "9,5", "10", "11", "12", "13", "14", "15", "16", "17", "1", "2", "3", "4", "5", "6", "7", "8", "16,5", "9", "1,5", "15,5", "14,5", "2,5", "13,5", "3,5", "12,5", "4,5", "10,5", "11,5", "5,5", "6,5"], "featureRelevance": ["FILTER"], "relevance": "LOW", "description": "", "reference": ""}, {"name": "Optik", "attributeGroup": "Optik/Stil", "type": "STRING", "multiValue": true, "featureRelevance": ["PRODUCT_DETAILS"], "relevance": "LOW", "description": "", "exampleValues": ["unifarben", "bedruckt", "gemustert", "gestreift", "gebl\u00fcmt"], "recommendedValues": ["Rautenmuster", "Rhombenmuster", "unifarben mit Farbeinsatz", "Hahnentrittmuster", "Glitzermuster", "Fischgratmuster", "Nadelstreifen", "tarnfarben", "ethno", "Glencheckmuster"], "reference": ""}, {"name": "Gr\u00f6\u00dfensystem", "attributeGroup": "Gr\u00f6\u00dfentext", "type": "STRING", "multiValue": false, "featureRelevance": [], "relevance": "LOW", "description": "", "exampleValues": ["EU-Gr\u00f6\u00dfen", "US-Gr\u00f6\u00dfen"], "reference": ""}, {"name": "Geschlecht", "attributeGroup": "Allgemein", "type": "STRING", "multiValue": false, "allowedValues": ["neutral", "m\u00e4nnlich", "weiblich"], "featureRelevance": ["NAVIGATION", "FILTER", "SEARCH"], "relevance": "HIGH", "description": "", "reference": ""}, {"name": "Materialart", "attributeGroup": "Material", "type": "STRING", "multiValue": false, "featureRelevance": ["VARIATION_THEME", "FILTER", "NAVIGATION", "SEARCH", "PRODUCT_DETAILS"], "relevance": "LOW", "description": "", "exampleValues": ["Jersey", "Web", "Fleece", "Interlock", "Stoff"], "recommendedValues": ["Softshell", "Single Jersey", "Jersey"], "reference": ""}, {"name": "Langgr\u00f6\u00dfen", "attributeGroup": "Gr\u00f6\u00dfensystem", "type": "INTEGER", "multiValue": true, "allowedValues": ["88", "68", "120", "110", "100", "112", "102", "114", "104", "116", "106", "90", "118", "80", "108", "92", "82", "72", "94", "84", "96", "86", "76", "98"], "featureRelevance": ["FILTER"], "relevance": "LOW", "description": "", "reference": ""}, {"name": "Bundweite", "attributeGroup": "Gr\u00f6\u00dfensystem", "type": "INTEGER", "multiValue": true, "allowedValues": ["33", "44", "23", "34", "24", "35", "46", "25", "36", "26", "48", "27", "38", "28", "29", "50", "40", "30", "31", "42", "32"], "featureRelevance": ["FILTER"], "relevance": "LOW", "description": "", "reference": ""}, {"name": "Gr\u00f6\u00dfentyp", "attributeGroup": "Gr\u00f6\u00dfentext", "type": "STRING", "multiValue": true, "featureRelevance": [], "relevance": "MEDIUM", "description": "", "exampleValues": ["Normalgr\u00f6\u00dfen", "Kurzgr\u00f6\u00dfen"], "reference": ""}, {"name": "Kurzgr\u00f6\u00dfen", "attributeGroup": "Gr\u00f6\u00dfensystem", "type": "INTEGER", "multiValue": true, "allowedValues": ["22", "33", "23", "34", "24", "35", "25", "26", "16", "27", "17", "28", "18", "29", "19", "30", "20", "31", "21", "32"], "featureRelevance": ["FILTER"], "relevance": "LOW", "description": "", "reference": ""}, {"name": "Schnittform L\u00e4nge", "attributeGroup": "Passform/Schnitt", "type": "STRING", "multiValue": false, "featureRelevance": ["VARIATION_THEME", "NAVIGATION", "PRODUCT_DETAILS"], "relevance": "LOW", "description": "", "exampleValues": ["lang", "kurz", "normal", "7/8-L\u00e4nge", "kn\u00f6chellang"], "recommendedValues": ["kurz", "ca. Mitte Oberschenkel", "knieumspielend", "mini", "kniebedeckend", "Po-bedeckend", "bodenlang", "h\u00fcftlang", "extrakurz", "taillenlang", "ca. Mitte Knie", "kniefrei", "h\u00fcftbedeckend", "bauchfrei"], "reference": ""}, {"name": "\u00c4rmel", "attributeGroup": "Passform/Schnitt", "type": "STRING", "multiValue": false, "featureRelevance": ["PRODUCT_DETAILS"], "relevance": "LOW", "description": "", "exampleValues": ["ohne \u00c4rmel", "Langarm", "Kurzarm", "3/4-\u00c4rmel", "Halbarm"], "recommendedValues": ["Kurzarm + Langarm"], "reference": ""}, {"name": "US-Gr\u00f6\u00dfen", "attributeGroup": "Gr\u00f6\u00dfensystem", "type": "STRING", "multiValue": true, "allowedValues": ["14XL", "12XL", "10XL", "4XL", "5XL", "6XL", "7XL", "8XL", "L", "9XL", "M", "XXL", "XXS", "S", "XL", "XS", "XXXL"], "featureRelevance": ["FILTER"], "relevance": "MEDIUM", "description": "", "reference": ""}, {"name": "Farbe", "attributeGroup": "Farbe", "type": "STRING", "multiValue": false, "featureRelevance": ["VARIATION_THEME", "TOPINFO", "PRODUCT_DETAILS"], "relevance": "HIGH", "description": "", "exampleValues": ["schwarz", "wei\u00df", "blau", "marine", "grau"], "reference": ""}, {"name": "Verschluss", "attributeGroup": "Details", "type": "STRING", "multiValue": true, "featureRelevance": ["PRODUCT_DETAILS"], "relevance": "LOW", "description": "", "exampleValues": ["Rei\u00dfverschluss", "Knopfleiste", "Druckkn\u00f6pfe", "Band", "Gummizug"], "reference": ""}, {"name": "Tr\u00e4ger", "attributeGroup": "Passform/Schnitt", "type": "STRING", "multiValue": false, "featureRelevance": ["PRODUCT_DETAILS"], "relevance": "LOW", "description": "", "exampleValues": ["mit Tr\u00e4ger", "Spaghettitr\u00e4ger", "ohne Tr\u00e4ger", "Tanktoptr\u00e4ger", "Neckholder"], "reference": ""}, {"name": "US-Gr\u00f6\u00dfen (Kinder)", "attributeGroup": "Gr\u00f6\u00dfensystem", "type": "STRING", "multiValue": true, "allowedValues": ["4XL", "5XL", "L", "2XS", "M", "XXL", "3XS", "XXS", "XXXS", "S", "XL", "XS", "XXXL"], "featureRelevance": ["FILTER"], "relevance": "LOW", "description": "", "reference": ""}, {"name": "UK-Gr\u00f6\u00dfen", "attributeGroup": "Gr\u00f6\u00dfensystem", "type": "INTEGER", "multiValue": true, "allowedValues": ["22", "44", "24", "46", "26", "48", "28", "50", "30", "52", "10", "32", "12", "34", "14", "36", "16", "38", "18", "2", "4", "6", "8", "40", "41", "20", "42"], "featureRelevance": ["FILTER"], "relevance": "LOW", "description": "", "reference": ""}, {"name": "Pflegehinweise", "attributeGroup": "Material", "type": "STRING", "multiValue": true, "featureRelevance": ["PRODUCT_DETAILS"], "relevance": "HIGH", "description": "", "exampleValues": ["Maschinenw\u00e4sche", "Schonw\u00e4sche", "Handw\u00e4sche", "Reinigung", "Lederreinigung"], "reference": ""}, {"name": "Normalgr\u00f6\u00dfen (Kinder)", "attributeGroup": "Gr\u00f6\u00dfensystem", "type": "INTEGER", "multiValue": true, "allowedValues": ["44", "68", "170", "152", "110", "176", "134", "158", "116", "92", "50", "74", "98", "56", "182", "140", "164", "122", "166", "188", "146", "168", "104", "128", "80", "40", "62", "86"], "featureRelevance": ["FILTER"], "relevance": "LOW", "description": "", "reference": ""}], "lastModified": "2020-12-03T02:39:43.718Z"}